MowzFinder/Main.py
MowzFinder/__init__.py
MowzFinder-1.1.1.dist-info/METADATA
MowzFinder-1.1.1.dist-info/WHEEL
MowzFinder-1.1.1.dist-info/top_level.txt
MowzFinder-1.1.1.dist-info/RECORD
